LICENSE.md
MANIFEST.in
README.md
setup.py
fremake_canopy.egg-info/PKG-INFO
fremake_canopy.egg-info/SOURCES.txt
fremake_canopy.egg-info/dependency_links.txt
fremake_canopy.egg-info/requires.txt
fremake_canopy.egg-info/top_level.txt
gfdl_fremake/__init__.py
gfdl_fremake/buildBaremetal.py
gfdl_fremake/buildDocker.py
gfdl_fremake/checkout.py
gfdl_fremake/fremake
gfdl_fremake/makefilefre.py
gfdl_fremake/platformfre.py
gfdl_fremake/schema.json
gfdl_fremake/targetfre.py
gfdl_fremake/varsfre.py
gfdl_fremake/yamlfre.py
gfdl_fremake/yamls/am5.yaml
gfdl_fremake/yamls/compile.yaml
gfdl_fremake/yamls/platforms.yaml
gfdl_fremake/yamls/schema.json