Metadata-Version: 2.1
Name: fremake-canopy
Version: 0.1.3
Summary: Implementation of fremake
Author: Thomas Robinson, Dana Singh, Bennett Chang
Author-email: Thomas.Robinson@noaa.gov
License-File: LICENSE.md
